<?xml version="1.0" encoding="UTF-8"?>
<!DOCTYPE coverity SYSTEM "coverity_config.dtd">
<coverity>
<!-- THIS FILE IS AUTOMATICALLY GENERATED - YOU MAY ADD XML ENTITIES -->
<!-- TO UPDATE THE COMPILER CONFIGURATION AFTER THE begin_command_line_config CLOSING TAG. -->
    <cit_version>1</cit_version>
    <config>
      <build>
        <compiler>
          <template_compiler>true</template_compiler>
          <comp_name>javaw</comp_name>
          <comp_translator>javaw</comp_translator>
          <comp_lang>Static Java</comp_lang>
          <comp_generic>java</comp_generic>
        </compiler>
        <options>
          <id>javaw-javaw-.*</id>
          <begin_command_line_config></begin_command_line_config>
        </options>
      </build>
    </config>
    <md5>aa3bf49b5164470df847ce74b96aa069</md5>
</coverity>

